{
  "chapters": {
    "1": {
      "pendingViews": 1,
      "lastIncrement": "2026-01-03T00:31:28.342Z",
      "lastUpdate": "2026-01-03T00:12:12+07:00"
    },
    "2": {
      "pendingViews": 1,
      "lastIncrement": "2026-01-03T00:35:26.042Z",
      "lastUpdate": "2026-01-03T00:12:12+07:00"
    },
    "3": {
      "pendingViews": 1,
      "lastIncrement": "2026-01-03T00:40:48.499Z",
      "lastUpdate": "2026-01-03T00:12:12+07:00"
    },
    "4": {
      "pendingViews": 1,
      "lastIncrement": "2026-01-03T00:46:23.072Z",
      "lastUpdate": "2026-01-03T00:12:12+07:00"
    },
    "5": {
      "pendingViews": 1,
      "lastIncrement": "2026-01-03T00:49:52.497Z",
      "lastUpdate": "2026-01-03T00:12:12+07:00"
    },
    "6": {
      "pendingViews": 1,
      "lastIncrement": "2026-01-03T00:53:36.573Z",
      "lastUpdate": "2026-01-03T00:12:12+07:00"
    },
    "7": {
      "pendingViews": 1,
      "lastIncrement": "2026-01-03T00:57:32.764Z",
      "lastUpdate": "2026-01-03T00:12:12+07:00"
    },
    "8": {
      "pendingViews": 1,
      "lastIncrement": "2026-01-03T01:02:02.439Z",
      "lastUpdate": "2026-01-03T00:12:12+07:00"
    },
    "9": {
      "pendingViews": 1,
      "lastIncrement": "2026-01-03T01:07:46.060Z",
      "lastUpdate": "2026-01-03T00:12:12+07:00"
    },
    "8.5": {
      "pendingViews": 1,
      "lastIncrement": "2026-01-03T01:06:55.270Z",
      "lastUpdate": "2026-01-03T00:12:12+07:00"
    },
    "10.1": {
      "pendingViews": 1,
      "lastIncrement": "2026-01-03T01:13:41.174Z",
      "lastUpdate": "2026-01-03T00:12:12+07:00"
    },
    "10.2": {
      "pendingViews": 1,
      "lastIncrement": "2026-01-03T01:15:27.172Z",
      "lastUpdate": "2026-01-03T00:12:12+07:00"
    },
    "11.1": {
      "pendingViews": 1,
      "lastIncrement": "2026-01-03T01:18:06.684Z",
      "lastUpdate": "2026-01-03T00:12:12+07:00"
    },
    "11.2": {
      "pendingViews": 1,
      "lastIncrement": "2026-01-03T01:20:06.366Z",
      "lastUpdate": "2026-01-03T00:12:12+07:00"
    },
    "12.1": {
      "pendingViews": 1,
      "lastIncrement": "2026-01-03T01:22:01.897Z",
      "lastUpdate": "2026-01-03T00:12:12+07:00"
    },
    "12.2": {
      "pendingViews": 4,
      "lastIncrement": "2026-01-03T01:24:30.218Z",
      "lastUpdate": "2026-01-03T00:12:12+07:00"
    },
    "13.1": {
      "pendingViews": 2,
      "lastIncrement": "2026-01-03T01:26:12.038Z",
      "lastUpdate": "2026-01-03T00:12:12+07:00"
    },
    "13.2": {
      "pendingViews": 2,
      "lastIncrement": "2026-01-03T01:27:46.578Z",
      "lastUpdate": "2026-01-03T00:12:12+07:00"
    },
    "14.1": {
      "pendingViews": 2,
      "lastIncrement": "2026-01-03T01:29:56.081Z",
      "lastUpdate": "2026-01-03T00:12:12+07:00"
    },
    "14.2": {
      "pendingViews": 2,
      "lastIncrement": "2026-01-03T01:32:11.793Z",
      "lastUpdate": "2026-01-03T00:12:12+07:00"
    },
    "15.1": {
      "pendingViews": 2,
      "lastIncrement": "2026-01-03T01:34:24.707Z",
      "lastUpdate": "2026-01-03T00:12:12+07:00"
    },
    "15.2": {
      "pendingViews": 4,
      "lastIncrement": "2026-01-03T01:36:03.111Z",
      "lastUpdate": "2026-01-03T00:12:12+07:00"
    },
    "16.1": {
      "pendingViews": 2,
      "lastIncrement": "2026-01-03T01:38:19.133Z",
      "lastUpdate": "2026-01-03T00:12:12+07:00"
    },
    "16.2": {
      "pendingViews": 3,
      "lastIncrement": "2026-01-03T05:23:10.568Z",
      "lastUpdate": "2026-01-03T00:12:12+07:00"
    },
    "17.1": {
      "pendingViews": 7,
      "lastIncrement": "2026-01-03T05:23:57.655Z",
      "lastUpdate": "2026-01-03T00:12:12+07:00"
    },
    "17.2": {
      "pendingViews": 14,
      "lastIncrement": "2026-01-03T06:06:41.911Z",
      "lastUpdate": "2026-01-03T00:12:12+07:00"
    },
    "18.1": {
      "pendingViews": 4,
      "lastIncrement": "2026-01-03T06:09:11.827Z",
      "lastUpdate": "2026-01-03T00:12:12+07:00"
    }
  },
  "lastUpdated": "2026-01-01T00:11:54+07:00"
}