{
  "chapters": {
    "1": {
      "pendingViews": 0,
      "lastIncrement": "2026-02-17T02:49:34.157Z",
      "lastUpdate": "2026-02-18T00:50:17+07:00"
    },
    "2": {
      "pendingViews": 0,
      "lastIncrement": "2026-02-17T02:51:10.476Z",
      "lastUpdate": "2026-02-18T00:50:17+07:00"
    },
    "3": {
      "pendingViews": 0,
      "lastIncrement": "2026-02-17T02:55:40.354Z",
      "lastUpdate": "2026-02-18T00:50:17+07:00"
    },
    "4": {
      "pendingViews": 0,
      "lastIncrement": "2026-02-17T02:58:04.037Z",
      "lastUpdate": "2026-02-18T00:50:17+07:00"
    },
    "5": {
      "pendingViews": 0,
      "lastIncrement": "2026-02-17T02:58:39.931Z",
      "lastUpdate": "2026-02-18T00:50:17+07:00"
    },
    "6": {
      "pendingViews": 0,
      "lastIncrement": "2026-02-17T02:59:33.432Z",
      "lastUpdate": "2026-02-18T00:50:17+07:00"
    },
    "7": {
      "pendingViews": 0,
      "lastIncrement": "2026-02-17T03:05:59.297Z",
      "lastUpdate": "2026-02-18T00:50:17+07:00"
    },
    "8": {
      "pendingViews": 1,
      "lastIncrement": "2026-02-18T20:47:04.884Z",
      "lastUpdate": "2026-02-18T00:50:17+07:00"
    },
    "9": {
      "pendingViews": 1,
      "lastIncrement": "2026-02-18T20:50:22.884Z",
      "lastUpdate": "2026-02-18T00:50:17+07:00"
    },
    "8.5": {
      "pendingViews": 1,
      "lastIncrement": "2026-02-18T20:49:45.697Z",
      "lastUpdate": "2026-02-18T00:50:17+07:00"
    },
    "10.1": {
      "pendingViews": 2,
      "lastIncrement": "2026-02-18T20:52:13.415Z",
      "lastUpdate": "2026-02-17T00:32:15+07:00"
    },
    "10.2": {
      "pendingViews": 1,
      "lastIncrement": "2026-02-18T20:53:06.806Z",
      "lastUpdate": "2026-02-17T00:32:15+07:00"
    },
    "11.1": {
      "pendingViews": 0,
      "lastIncrement": "2026-02-16T11:44:24.987Z",
      "lastUpdate": "2026-02-17T00:32:15+07:00"
    },
    "11.2": {
      "pendingViews": 0,
      "lastIncrement": "2026-02-16T11:45:23.363Z",
      "lastUpdate": "2026-02-17T00:32:15+07:00"
    },
    "12.1": {
      "pendingViews": 0,
      "lastIncrement": "2026-02-16T11:47:03.233Z",
      "lastUpdate": "2026-02-17T00:32:15+07:00"
    },
    "12.2": {
      "pendingViews": 0,
      "lastIncrement": "2026-02-16T11:48:52.170Z",
      "lastUpdate": "2026-02-17T00:32:15+07:00"
    },
    "13.1": {
      "pendingViews": 0,
      "lastIncrement": "2026-02-16T11:50:19.238Z",
      "lastUpdate": "2026-02-17T00:32:15+07:00"
    },
    "13.2": {
      "pendingViews": 0,
      "lastIncrement": "2026-02-16T11:51:46.647Z",
      "lastUpdate": "2026-02-17T00:32:15+07:00"
    },
    "14.1": {
      "pendingViews": 0,
      "lastIncrement": "2026-02-16T11:53:22.727Z",
      "lastUpdate": "2026-02-17T00:32:15+07:00"
    },
    "14.2": {
      "pendingViews": 0,
      "lastIncrement": "2026-02-16T11:54:53.458Z",
      "lastUpdate": "2026-02-17T00:32:15+07:00"
    },
    "15.1": {
      "pendingViews": 0,
      "lastIncrement": "2026-02-16T11:56:00.702Z",
      "lastUpdate": "2026-02-17T00:32:15+07:00"
    },
    "15.2": {
      "pendingViews": 0,
      "lastIncrement": "2026-02-16T11:57:27.972Z",
      "lastUpdate": "2026-02-17T00:32:15+07:00"
    },
    "16.1": {
      "pendingViews": 0,
      "lastIncrement": "2026-02-16T11:59:27.540Z",
      "lastUpdate": "2026-02-17T00:32:15+07:00"
    },
    "16.2": {
      "pendingViews": 0,
      "lastIncrement": "2026-02-16T12:01:03.188Z",
      "lastUpdate": "2026-02-17T00:32:15+07:00"
    },
    "17.1": {
      "pendingViews": 0,
      "lastIncrement": "2026-02-16T12:01:54.262Z",
      "lastUpdate": "2026-02-17T00:32:15+07:00"
    },
    "17.2": {
      "pendingViews": 0,
      "lastIncrement": "2026-02-16T12:03:16.307Z",
      "lastUpdate": "2026-02-17T00:32:15+07:00"
    },
    "18.1": {
      "pendingViews": 1,
      "lastIncrement": "2026-02-18T23:21:16.516Z",
      "lastUpdate": "2026-02-19T00:48:02+07:00"
    },
    "18.2": {
      "pendingViews": 2,
      "lastIncrement": "2026-02-18T23:21:02.862Z",
      "lastUpdate": "2026-02-19T00:48:02+07:00"
    }
  },
  "lastUpdated": "2026-01-01T00:11:54+07:00"
}